{
	"$schema": "https://biomejs.dev/schemas/1.9.4/schema.json",
	"extends": [],
	"formatter": {
		"enabled": true,
		"indentStyle": "space",
		"indentWidth": 2,
		"lineWidth": 80
	},
	"organizeImports": {
		"enabled": true
	},
	"javascript": {
		"formatter": {
			"semicolons": "always",
			"quoteStyle": "double",
			"trailingCommas": "es5",
			"bracketSpacing": true,
			"bracketSameLine": false,
			"arrowParentheses": "asNeeded"
		}
	},
	"linter": {
		"enabled": true,
		"rules": {
			"recommended": false,
			"suspicious": {
				"recommended": false,
				"noConsole": {
					"level": "warn",
					"options": {
						"allow": ["warn", "error"]
					}
				},
				"noExplicitAny": "warn",
				"noArrayIndexKey": "off"
			},
			"style": {
				"recommended": false,
				"noNonNullAssertion": "warn",
				"useTemplate": "error",
				"useConst": "error",
				"noVar": "error",
				"useImportType": "off",
				"useNumberNamespace": "off",
				"useNodejsImportProtocol": "off"
			},
			"correctness": {
				"recommended": false,
				"noUnusedImports": "error",
				"noUnusedVariables": "error",
				"useExhaustiveDependencies": "off"
			},
			"complexity": {
				"recommended": false,
				"noForEach": "off"
			}
		}
	},
	"files": {
		"ignore": [
			"node_modules",
			".next",
			"out",
			"build",
			"dist",
			"coverage",
			".source",
			".storybook",
			".augment",
			".trae",
			".pnpm-store",
			".eslintcache",
			"pnpm-lock.yaml",
			"package-lock.json",
			"yarn.lock",
			"**/*.config.js",
			"**/*.config.mjs",
			"next-env.d.ts",
			".env*",
			"*.log",
			"pids",
			"*.pid",
			"*.seed",
			"*.pid.lock",
			".npm",
			".pnp",
			".pnp.js",
			"**/*.tsbuildinfo",
			"playwright-report",
			"test-results",
			"content/docs/**/*.mdx",
			"content/slides/**/*.md",
			".github/prompts/openspec-apply.prompt.md",
			".github/prompts/openspec-archive.prompt.md",
			".github/prompts/openspec-proposal.prompt.md",
			"openspec/AGENTS.md",
			"AGENTS.md"
		]
	},
	"overrides": [
		{
			"include": ["app/**/*.{ts,tsx,js,jsx}"],
			"ignore": ["app/_actions/**", "app/api/**"],
			"linter": {
				"rules": {
					"nursery": {
						"noRestrictedImports": {
							"level": "error",
							"options": {
								"paths": {
									"@/domains/**": "App layer should call backend through server actions or API clients instead of importing domains."
								}
							}
						}
					}
				}
			}
		}
	]
}
